flow_tuning/__init__.py
flow_tuning/algorithms/base.py
flow_tuning/algorithms/orion_turbo.py
flow_tuning/algorithms/power_tuning.py
flow_tuning/cli.py
flow_tuning/function.py
flow_tuning/generators/base.py
flow_tuning/generators/basic.py
flow_tuning/providers/aliyun.py
flow_tuning/providers/aws.py
flow_tuning/providers/base.py
flow_tuning/utils/console.py
flow_tuning/utils/module_loader.py
flow_tuning/workflow.py
flow_tuning-0.1.2.dist-info/METADATA
flow_tuning-0.1.2.dist-info/WHEEL
flow_tuning-0.1.2.dist-info/entry_points.txt
flow_tuning-0.1.2.dist-info/RECORD
